README.rst
setup.py
src/__init__.py
src/__version__.py
src/main.py
src/djdzippath.egg-info/PKG-INFO
src/djdzippath.egg-info/SOURCES.txt
src/djdzippath.egg-info/dependency_links.txt
src/djdzippath.egg-info/not-zip-safe
src/djdzippath.egg-info/top_level.txt