Metadata-Version: 1.2
Name: djdzippath
Version: 1.0.3
Summary: zip path
Home-page: https://heifade.com
Author: heifade
Author-email: heifade@126.com
License: UNKNOWN
Keywords: test
Platform: UNKNOWN
Requires-Python: >=3.0, !=3.0.*, !=3.1.*, !=3.2.*, !=3.3*
